aulm_chatbots
