Metadata-Version: 2.1
Name: auglm-chatbots
Version: 0.0.9
Home-page: https://github.com/alex4321/gpt3-retrieving-bot
Author: Alexander Pozharskii
Author-email: gaussmake@gmail.com
License-File: LICENSE
